{"train_id": "A1", "position": [28.815, 77.063]}{"train_id": "A1", "position": [28.7359, 77.112]}{"train_id": "A1", "position": [28.7395, 77.10810000000001]}{"train_id": "A1", "position": [28.7431, 77.1042]}{"train_id": "A1", "position": [28.7431, 77.1042]}{"train_id": "A1", "position": [28.74705, 77.09985]}{"train_id": "A1", "position": [28.751, 77.0955]}{"train_id": "A1", "position": [28.751, 77.0955]}{"train_id": "A1", "position": [28.75485, 77.09055000000001]}{"train_id": "A1", "position": [28.7587, 77.0856]}{"train_id": "A1", "position": [28.7587, 77.0856]}{"train_id": "A1", "position": [28.761666666666667, 77.0823]}{"train_id": "A1", "position": [28.764633333333332, 77.079]}{"train_id": "A1", "position": [28.7676, 77.0757]}{"train_id": "A1", "position": [28.770566666666667, 77.0724]}{"train_id": "A1", "position": [28.773533333333333, 77.06909999999999]}{"train_id": "A1", "position": [28.7765, 77.0658]}{"train_id": "A1", "position": [28.7765, 77.0658]}{"train_id": "A1", "position": [28.78025, 77.06558333333334]}{"train_id": "A1", "position": [28.784, 77.06536666666666]}{"train_id": "A1", "position": [28.78775, 77.06514999999999]}{"train_id": "A1", "position": [28.7915, 77.06493333333333]}{"train_id": "A1", "position": [28.79525, 77.06471666666667]}{"train_id": "A1", "position": [28.799, 77.0645]}{"train_id": "A1", "position": [28.799, 77.0645]}{"train_id": "A1", "position": [28.804333333333332, 77.064]}{"train_id": "A1", "position": [28.80966666666667, 77.0635]}{"train_id": "A1", "position": [28.815, 77.063]}{"train_id": "A1", "position": [28.815, 77.063]}{"train_id": "A1", "position": [28.819333333333333, 77.06083333333333]}{"train_id": "A1", "position": [28.823666666666668, 77.05866666666667]}{"train_id": "A1", "position": [28.828, 77.0565]}{"train_id": "A1", "position": [28.828, 77.0565]}{"train_id": "A1", "position": [28.831, 77.05433333333333]}{"train_id": "A1", "position": [28.834, 77.05216666666666]}{"train_id": "A1", "position": [28.837, 77.05]}